setup.py
timeparser.py
py_timeparser.egg-info/PKG-INFO
py_timeparser.egg-info/SOURCES.txt
py_timeparser.egg-info/dependency_links.txt
py_timeparser.egg-info/top_level.txt