Metadata-Version: 1.0
Name: py-timeparser
Version: 0.3.2
Summary: Parse time string (e.g. 1h5min)
Home-page: https://github.com/utgwkk/py-timeparser
Author: utgwkk
Author-email: utagawa.kiki@gmail.com
License: MIT
Platform: UNKNOWN
